<?xml version="1.0" encoding="UTF-8"?>
<tv>
  <channel id="airy-607">
    <display-name>Peak TV</display-name>
    <icon src="" />
  </channel>
  <programme start="20260708000000 +0000" stop="20260708013000 +0000" channel="airy-607">
    <title>Rim of the Canyon</title>
    <desc>ene Autrys stolen horse turns up in a ghost town where Gene goes after he is left stranded during a stagecoach race</desc>
  </programme>
  <programme start="20260708013000 +0000" stop="20260708023000 +0000" channel="airy-607">
    <title>Lights of Old Sante Fe</title>
    <desc>In this musical western Marjorie Brooks Dale Evans is the owner and operator of a rodeo thats an antiquated touring company on its last legs Her business rival Frank Madden Richard Powers offers to combine their operations if the lovely Marjorie will be his bride Though she initially rebuffs his proposal a canceled booking tips the scales and forces Marjorie to accept But rodeo rider Roy Rogers Roy Rogers suspects Frank is behind Marjories troubles and sets out to investigate </desc>
  </programme>
  <programme start="20260708023000 +0000" stop="20260708033000 +0000" channel="airy-607">
    <title>The Mystery of the Hooded Horsemen</title>
    <desc>In a small frontier mining town a gang of outlaws in black hoods is running roughshod over locals presiding over a reign of terror Tex Tex Ritter and Stubby Horace Murphy take up the dying wish of Tom Lafe McKee a kindly rancher killed by the gang to capture the marauders Knowing that the survival of the local mine and the heart of Toms sweet daughter Iris Meredith are on the line Tex and Stubby go undercover in the gang hoping to bring them down from the inside</desc>
  </programme>
  <programme start="20260708033000 +0000" stop="20260708050000 +0000" channel="airy-607">
    <title>Trail Street</title>
    <desc>Bat Mastersons old friend Billy Burns convinces him to become marshal of Liberal Kansas and help the residents fight drought and a destructive range war</desc>
  </programme>
  <programme start="20260708050000 +0000" stop="20260708060000 +0000" channel="airy-607">
    <title>Filler</title>
    <desc>Filler</desc>
  </programme>
  <programme start="20260708060000 +0000" stop="20260708063000 +0000" channel="airy-607">
    <title>DefaultFiller</title>
    <desc>DefaultFiller</desc>
  </programme>
  <programme start="20260708063000 +0000" stop="20260708070000 +0000" channel="airy-607">
    <title>DefaultFiller</title>
    <desc>DefaultFiller</desc>
  </programme>
  <programme start="20260708070000 +0000" stop="20260708080000 +0000" channel="airy-607">
    <title>The Money Pit</title>
    <desc>A young couple struggles to repair a hopelessly dilapidated house</desc>
  </programme>
  <channel id="airy-631">
    <display-name>Best of Times</display-name>
    <icon src="" />
  </channel>
  <programme start="20260708000000 +0000" stop="20260708010000 +0000" channel="airy-631">
    <title>The Wild Wild West</title>
    <desc>To warn some of the countrys wealthiest men about recurrent murders Agents West and Gordon visit Curtis Dodd who could become the next victim Dodd who is playing the piano is killed as a lethal spear is fired from the piano keys Through a series of clues West and Gordon realize that murdered men were all married to younger women whose marriages were arranged by matchmaker Emma Valentine</desc>
  </programme>
  <programme start="20260708010000 +0000" stop="20260708013000 +0000" channel="airy-631">
    <title>Dragnet</title>
    <desc>Friday and Gannon investigate a series of burglaries that are taking place during the day and the victims are those with a recent wedding or death in the family A senior citizen uses the paper to find homes that are empty during the day</desc>
  </programme>
  <programme start="20260708013000 +0000" stop="20260708020000 +0000" channel="airy-631">
    <title>Dragnet </title>
    <desc>An ex-con who places an ad in a newspaper gets a reply referring to making a killing for 1000 He turns the reply over to Friday and Gannon who investigate the possibility that the replier is soliciting murder</desc>
  </programme>
  <programme start="20260708020000 +0000" stop="20260708030000 +0000" channel="airy-631">
    <title>The Fugitive </title>
    <desc>A hated construction company owner with a heart condition recognizes Kimble and forces him to be his office assistant because of his doctor skills</desc>
  </programme>
  <programme start="20260708030000 +0000" stop="20260708033000 +0000" channel="airy-631">
    <title>Sea Hunt </title>
    <desc>A beautiful millionairess who was crippled by a mountain climbing accident has her husband and doctor recommend scuba diving as therapy for her legs Nelson is hired to work with her The husband has an ulterior motive and it involves the strong currents at 60 feet below Drakes Head on the Pacific Coast</desc>
  </programme>
  <programme start="20260708033000 +0000" stop="20260708040000 +0000" channel="airy-631">
    <title>Sea Hunt </title>
    <desc>Mike conducts a desperate search for survivors soon after a freighter sinks to the bottom of a river in the city of New York He finds two trapped men and a dog named Tiger surviving in an air pocket He must quickly find a way to save the men - and Tiger too</desc>
  </programme>
  <programme start="20260708040000 +0000" stop="20260708050000 +0000" channel="airy-631">
    <title>12 OClock High</title>
    <desc>Gen Savage decides to court martial a captain who broke formation to provide air cover for a crew bailing out of a plane creating much anger</desc>
  </programme>
  <programme start="20260708050000 +0000" stop="20260708053000 +0000" channel="airy-631">
    <title>Dark Shadows</title>
    <desc>Barnabas is angered when Julia jealously snaps at Victoria</desc>
  </programme>
  <programme start="20260708053000 +0000" stop="20260708060000 +0000" channel="airy-631">
    <title>Dark Shadows</title>
    <desc>Barnabas feels so well from the treatments that he decides to ask Victoria to sit and watch the sunrise with him so Julia hypnotizes her and shows Vicki where Barnabas slumbers</desc>
  </programme>
  <programme start="20260708060000 +0000" stop="20260708063000 +0000" channel="airy-631">
    <title>Dark Shadows</title>
    <desc>When Barnabas begins aging Julia tries to reverse the process Meanwhile David offers Carolyn the toy soldier for protection which lands her a visit from Sarah</desc>
  </programme>
  <programme start="20260708063000 +0000" stop="20260708070000 +0000" channel="airy-631">
    <title>Dark Shadows</title>
    <desc>Julias treatments backfire and Barnabas shows his true age so she suggests he replenish his blood with Victorias Meanwhile Carolyn begins to have doubts that David was making up stories about Barnabas</desc>
  </programme>
  <programme start="20260708070000 +0000" stop="20260708080000 +0000" channel="airy-631">
    <title>Deadwood 76</title>
    <desc>A young drifter is mistaken for Billy the Kid The consequences prove deadly</desc>
  </programme>
  <channel id="airy-605">
    <display-name>Shattered TV</display-name>
    <icon src="" />
  </channel>
  <programme start="20260708000000 +0000" stop="20260708020000 +0000" channel="airy-605">
    <title>Jaws of Satan</title>
    <desc>A preacher whose ancestors were cursed by Druids battles Satan who has taken the form of a huge snake</desc>
  </programme>
  <programme start="20260708020000 +0000" stop="20260708030000 +0000" channel="airy-605">
    <title>Fredy 112</title>
    <desc>Fredy 112</desc>
  </programme>
  <programme start="20260708030000 +0000" stop="20260708033000 +0000" channel="airy-605">
    <title>Tales from the Crypt </title>
    <desc>After the death penalty is abolished an executioner continues his former job through freelancing</desc>
  </programme>
  <programme start="20260708033000 +0000" stop="20260708040000 +0000" channel="airy-605">
    <title>Tales from the Crypt </title>
    <desc>A greedy woman makes the mistake of murdering her husband while an escaped mental patient dressed in a Santa Claus outfit is on the loose</desc>
  </programme>
  <programme start="20260708040000 +0000" stop="20260708043000 +0000" channel="airy-605">
    <title>The Hitchhiker </title>
    <desc>A sculptor uses a drifter and his own abused girlfriend to recreate a murdersuicide</desc>
  </programme>
  <programme start="20260708043000 +0000" stop="20260708050000 +0000" channel="airy-605">
    <title>The Hitchhiker </title>
    <desc>Smarmy and opportunistic reality TV show host Jerry Rulac does an expose on the wild punk nightclub scene for the latest segment of his television program Why Are You Here Jerry uncovers more than he bargained for when he decides to focus on troubled wealthy party girl Donette and her unpredictable gaggle of scary friends</desc>
  </programme>
  <programme start="20260708050000 +0000" stop="20260708053000 +0000" channel="airy-605">
    <title>Werewolf</title>
    <desc>Eric confronts the werewolf Nicholas Remy and discovers that he is more formidable an opponent than Skorzeny ever was</desc>
  </programme>
  <programme start="20260708053000 +0000" stop="20260708060000 +0000" channel="airy-605">
    <title>Werewolf</title>
    <desc>Eric comes to the aid of a blind woman with a talent for trick shooting he meets while working at a carnival when he learns that her fiancé plans on killing her for the insurance money</desc>
  </programme>
  <programme start="20260708060000 +0000" stop="20260708070000 +0000" channel="airy-605">
    <title>Forever Knight </title>
    <desc>A succession of murders lead Nick and Schanke to suspect the villain is hunting the citys most dangerous criminals for sport</desc>
  </programme>
  <programme start="20260708070000 +0000" stop="20260708080000 +0000" channel="airy-605">
    <title>Friday 13th the Series </title>
    <desc>Ryan and Micki search for a cursed mulcher which is the murder weapon of choice for a gardeners assistant</desc>
  </programme>
  <channel id="airy-632">
    <display-name>TTL TV</display-name>
    <icon src="" />
  </channel>
  <programme start="20260708000000 +0000" stop="20260708003000 +0000" channel="airy-632">
    <title>McHales Navy </title>
    <desc>McHale and The Boys have planned some entertainment for the Base Personnel but Binghamton puts a stop to it and orders McHale and his Crew to ferry him to a Staff Meeting so that he can keep an eye on them But after the 73 is put out of commission by a Japanese plane Binghamton if forced to do some entertaining of his own during a mission to obtain some fuel on a Japanese-held island</desc>
  </programme>
  <programme start="20260708003000 +0000" stop="20260708010000 +0000" channel="airy-632">
    <title>McHales Navy </title>
    <desc>While trying to impress a pretty Nurse Parker receives several serious blows to his morale and humiliated he puts in for a transfer Then complications arise when McHale The Crew and the Nurse work up a plan to try to help him to regain his self-esteem and change his mind</desc>
  </programme>
  <programme start="20260708010000 +0000" stop="20260708013000 +0000" channel="airy-632">
    <title>Gomer Pyle USMC</title>
    <desc>Gomer makes friends with a hillbilly named Branch</desc>
  </programme>
  <programme start="20260708013000 +0000" stop="20260708020000 +0000" channel="airy-632">
    <title>Gomer Pyle USMC</title>
    <desc>Troy is captured while trying to make contact with the underground in a small village At stake is micro-film information about a new type of bomb the Germans have developed</desc>
  </programme>
  <programme start="20260708020000 +0000" stop="20260708023000 +0000" channel="airy-632">
    <title>Gilligans Island </title>
    <desc>The hungry castaways find a wild duck on the island but they dont know whether to use it as food or attach a message to him and hope for rescue</desc>
  </programme>
  <programme start="20260708023000 +0000" stop="20260708030000 +0000" channel="airy-632">
    <title>Gilligans Island</title>
    <desc>Gilligans Christmas wish appears to be coming true when a radio broadcast tells them their rescue is imminent While they wait they recall the first days on the island when Gilligan lost the radio and transmitter</desc>
  </programme>
  <programme start="20260708030000 +0000" stop="20260708033000 +0000" channel="airy-632">
    <title>Real McCoys </title>
    <desc>Grampa begins neglecting Flora MacMichael when an attractive 50-year-old widow develops an interest in him</desc>
  </programme>
  <programme start="20260708033000 +0000" stop="20260708040000 +0000" channel="airy-632">
    <title>Real McCoys </title>
    <desc>Luke volunteers to coach Little Lukes baseball team but soon finds himself beset by constant interference and advice from the other boys fathers</desc>
  </programme>
  <programme start="20260708040000 +0000" stop="20260708043000 +0000" channel="airy-632">
    <title>Get Smart </title>
    <desc>Max must retrieve something from a member of the Russian womens swim team but cant remember her name</desc>
  </programme>
  <programme start="20260708043000 +0000" stop="20260708050000 +0000" channel="airy-632">
    <title>Get Smart </title>
    <desc>KAOS uses Hymie as a robotic assassin against the Chief</desc>
  </programme>
  <programme start="20260708050000 +0000" stop="20260708060000 +0000" channel="airy-632">
    <title>BJ and the Bear </title>
    <desc>BJ Callie and Stacks help BJs old friend Steven Thomas Ulysses Nathaniel Travis complete the filming of his television pilot Buster Crabbe is outstanding as an aging stuntman with a secret</desc>
  </programme>
  <programme start="20260708060000 +0000" stop="20260708063000 +0000" channel="airy-632">
    <title>Mister Ed</title>
    <desc>Mister Ed volunteers to be shot into outer space</desc>
  </programme>
  <programme start="20260708063000 +0000" stop="20260708070000 +0000" channel="airy-632">
    <title>Mister Ed </title>
    <desc>Through Rogers trickery Ed believes that he has a shameful heritage so he runs away from home</desc>
  </programme>
  <programme start="20260708070000 +0000" stop="20260708073000 +0000" channel="airy-632">
    <title>Hogans Heroes</title>
    <desc>There seems to be a traitor in the escaped prisoner pipeline and Hogan has to find him by following the escape route</desc>
  </programme>
  <programme start="20260708073000 +0000" stop="20260708080000 +0000" channel="airy-632">
    <title>Hogans Heroes</title>
    <desc>Carter receives a Dear John letter and wants to join the rest of the prisoners that escape and go home</desc>
  </programme>
  <channel id="airy-612">
    <display-name>PassTime TV</display-name>
    <icon src="" />
  </channel>
  <programme start="20260708000000 +0000" stop="20260708020000 +0000" channel="airy-612">
    <title>Mozambique 1964</title>
    <desc>An out-of-work and penniless American pilot is offered work in Mozambique and promptly becomes an unwitting pawn in a world of drug smuggling kidnap and murder</desc>
  </programme>
  <programme start="20260708020000 +0000" stop="20260708040000 +0000" channel="airy-612">
    <title>Morning Departure </title>
    <desc>Trouble arises when 12 men realize that only eight of them can escape from the sinking submarine that has collided with a mine left over from the war</desc>
  </programme>
  <programme start="20260708040000 +0000" stop="20260708060000 +0000" channel="airy-612">
    <title>What A Way To Go</title>
    <desc>A four-time widow discusses her four marriages in which all of her husbands became incredibly rich and died prematurely because of their drive to be rich</desc>
  </programme>
  <programme start="20260708060000 +0000" stop="20260708080000 +0000" channel="airy-612">
    <title>Genghis Khan</title>
    <desc>During the thirteenth century the shy Mongol boy Temujin Carlo Cura becomes the fearless leader Genghis Khan Omar Sharif who unites all Mongol tribes and conquers most of Asia Europe and the Middle East</desc>
  </programme>
  <channel id="airy-649">
    <display-name>RnR TV</display-name>
    <icon src="" />
  </channel>
  <programme start="20260708000000 +0000" stop="20260708013000 +0000" channel="airy-649">
    <title>The Strange and Deadly Occurance</title>
    <desc>Something or someone haunts a couples Robert Stack Vera Miles new home in the country</desc>
  </programme>
  <programme start="20260708013000 +0000" stop="20260708020000 +0000" channel="airy-649">
    <title>Filler</title>
    <desc>Filler</desc>
  </programme>
  <programme start="20260708020000 +0000" stop="20260708030000 +0000" channel="airy-649">
    <title>The Dukes of Hazzard</title>
    <desc>Hughie Hogg returns with his eye on the office of Hazzard County Sheriff He blackmails his Uncle Boss into supporting his campaign by threatening to take secretly taken photographs of his criminal activities to the FBI Coy and Vance decide to support incumbent Rosco while they collect enough evidence to derail Hughies campaign and run him out of town</desc>
  </programme>
  <programme start="20260708030000 +0000" stop="20260708040000 +0000" channel="airy-649">
    <title>Hercules</title>
    <desc>Hercules</desc>
  </programme>
  <programme start="20260708040000 +0000" stop="20260708050000 +0000" channel="airy-649">
    <title>Earth Final Conflict</title>
    <desc>A group of Resistance capture a volunteer from a Taelon program for youth Liam decides they may learn valuable information from her They also decide to send in one of their own as a volunteer to see what the program is teaching</desc>
  </programme>
  <programme start="20260708050000 +0000" stop="20260708060000 +0000" channel="airy-649">
    <title>War of the Worlds</title>
    <desc>Suzanne learns that a friend of hers has disappeared from his college campus Meanwhile the aliens are on campus in search of a bio-weapon</desc>
  </programme>
  <programme start="20260708060000 +0000" stop="20260708063000 +0000" channel="airy-649">
    <title>Swamp Thing</title>
    <desc>Trapped in a cave with Alec and facing death by suffocation Arcane reviews his life in a grand soliloquy He can lie to others but ultimately can he lie to himself</desc>
  </programme>
  <programme start="20260708063000 +0000" stop="20260708070000 +0000" channel="airy-649">
    <title>Swamp Thing</title>
    <desc>40 years ago a plane carrying valuable Egyptian antiquities and a mummy crashed in the swamp Arcane supports an expedition to find it but his interest is far more than financial</desc>
  </programme>
  <programme start="20260708070000 +0000" stop="20260708080000 +0000" channel="airy-649">
    <title>Space 1999</title>
    <desc>The Alphans encounter a miles-long ark from the planet Daria where the inhabitants have a very distinctive class separation</desc>
  </programme>
  <channel id="airy-651">
    <display-name>The Canyon</display-name>
    <icon src="" />
  </channel>
  <programme start="20260708000000 +0000" stop="20260708010000 +0000" channel="airy-651">
    <title>Big Valley </title>
    <desc>Heath arrives in a dying desert town only to find himself a visitor in a madhouse His hosts are five deranged people who play bizarre and deadly games with their infrequent guests Heaths role in their hellish fantasy the accused--on trial for rape and murder</desc>
  </programme>
  <programme start="20260708010000 +0000" stop="20260708020000 +0000" channel="airy-651">
    <title>Cheyenne</title>
    <desc>His gear stolen Cheyenne follows the thief and killer to a small town The outlaw has stopped there to see the sheriff - his father The sheriff resigns so Cheyenne takes the job and falls for a girl whos father was the sheriff</desc>
  </programme>
  <programme start="20260708020000 +0000" stop="20260708030000 +0000" channel="airy-651">
    <title>Young Riders</title>
    <desc>Young Riders</desc>
  </programme>
  <programme start="20260708030000 +0000" stop="20260708040000 +0000" channel="airy-651">
    <title>Lonesome Dove Outlaw Years</title>
    <desc>Lonesome Dove Outlaw Years</desc>
  </programme>
  <programme start="20260708040000 +0000" stop="20260708050000 +0000" channel="airy-651">
    <title>The Streets of San Francisco </title>
    <desc>Keller goes undercover as a draft dodger to investigate an AWOL Marines murder</desc>
  </programme>
  <programme start="20260708050000 +0000" stop="20260708060000 +0000" channel="airy-651">
    <title>Mission Impossible</title>
    <desc>Cinnamon poses as the wife of an archaeologist with a serious heart condition He needs to be rescued and an assassination plot needs to be foiled</desc>
  </programme>
  <programme start="20260708060000 +0000" stop="20260708063000 +0000" channel="airy-651">
    <title>Dragnet </title>
    <desc>Dragnet </desc>
  </programme>
  <programme start="20260708063000 +0000" stop="20260708070000 +0000" channel="airy-651">
    <title>Dragnet </title>
    <desc>Dragnet </desc>
  </programme>
  <programme start="20260708070000 +0000" stop="20260708080000 +0000" channel="airy-651">
    <title>The Fugitive </title>
    <desc>Dr Kimble still fleeing with the woman he loves decides to fake their deaths at sea hoping it will fool Lt Gerard forever</desc>
  </programme>
  <channel id="airy-549">
    <display-name>30A TV</display-name>
    <icon src="" />
  </channel>
  <programme start="20260708000000 +0000" stop="20260708003000 +0000" channel="airy-549">
    <title>Local News</title>
    <desc>Apalachicola Oyster Fishery A Climate of Change Sgt Paula Pendleton on Kelly Clarkson and; message in a bottle"</desc>
  </programme>
  <programme start="20260708003000 +0000" stop="20260708010000 +0000" channel="airy-549">
    <title>Business Network TV</title>
    <desc>Gary White with John Maxwell Method of Public Speaking Broadcasting Northwest Florida -Florida State University"</desc>
  </programme>
  <programme start="20260708010000 +0000" stop="20260708020000 +0000" channel="airy-549">
    <title>What to See And Do</title>
    <desc>Get Ahead at Your Farmers Market 4 Easy Tips BeachBilly Lifestyle visits Chipley Gator Farm at Orange Hill Red Snapper Fishing St George Island Port St Joe  Apa"</desc>
  </programme>
  <programme start="20260708020000 +0000" stop="20260708023000 +0000" channel="airy-549">
    <title>Outdoors</title>
    <desc>1929 Chris Craft 28ft Triple Cockpit   DEMO RIDE 1929 Chris Craft 28ft Triple Cockpit   DEMO RIDE Pt1 Fitness On The Beach with Edna BeachBilly Lifestyle How Cu"</desc>
  </programme>
  <programme start="20260708023000 +0000" stop="20260708030000 +0000" channel="airy-549">
    <title>Shopping</title>
    <desc>Coastin With Carol at Willow and Mercer Shop850 interviews Brad Burnette Coastin With Carol at Willow and Mercer Shop850 interviews Brad Burnette"</desc>
  </programme>
  <programme start="20260708030000 +0000" stop="20260708040000 +0000" channel="airy-549">
    <title>Local News</title>
    <desc>5 Reasons Why The Emerald Coast is Green EO Wilson BioPhilia Center Harrison Ford Niceville School Powerade Video Winner EO Wilson BioPhilia Center Harrison For"</desc>
  </programme>
  <programme start="20260708040000 +0000" stop="20260708053000 +0000" channel="airy-549">
    <title>Nothing Scripted</title>
    <desc>Nothing Scripted #FloridaMan Flat Earth Episode with Guest Ryan McNay"</desc>
  </programme>
  <programme start="20260708053000 +0000" stop="20260708061500 +0000" channel="airy-549">
    <title>Outdoors</title>
    <desc>Come spend the 4th of July with us on 30A Come spend the 4th of July with us on 30A"</desc>
  </programme>
  <programme start="20260708061500 +0000" stop="20260708070000 +0000" channel="airy-549">
    <title>Business Network TV</title>
    <desc>Luxe Life Discovered with Ronnie McBrayer Rusty Goat Retreat"</desc>
  </programme>
  <programme start="20260708070000 +0000" stop="20260708073000 +0000" channel="airy-549">
    <title>The 3 Julias</title>
    <desc>Pt1 Allison Porter Cooks Salmon The 3 Julias  30a TV Pt1 Shrimp on Rosemary Skewers The 3 Julias #juliachild Array Array"</desc>
  </programme>
  <programme start="20260708073000 +0000" stop="20260708080000 +0000" channel="airy-549">
    <title>Music Scene</title>
    <desc>Kickstand Jenny Official Music Video for the song Tonight Livin on 30A Song by Songwriter Kevin Carson Singer-songwriter Alias James family roots go back four g"</desc>
  </programme>
  <channel id="airy-536">
    <display-name>Thailand TV</display-name>
    <icon src="" />
  </channel>
  <programme start="20260708000000 +0000" stop="20260708003000 +0000" channel="airy-536">
    <title>Going Astray 11 screen version</title>
    <desc>Going Astray 11 screen version</desc>
  </programme>
  <programme start="20260708003000 +0000" stop="20260708010000 +0000" channel="airy-536">
    <title>Win Lose Forgive</title>
    <desc>Win Lose Forgive</desc>
  </programme>
  <programme start="20260708010000 +0000" stop="20260708013000 +0000" channel="airy-536">
    <title>Crossing Salween HD - Eng Subs</title>
    <desc>Crossing Salween HD - Eng Subs</desc>
  </programme>
  <programme start="20260708013000 +0000" stop="20260708020000 +0000" channel="airy-536">
    <title>Thai Poppy 1991full version</title>
    <desc>Thai Poppy 1991full version</desc>
  </programme>
  <programme start="20260708020000 +0000" stop="20260708023000 +0000" channel="airy-536">
    <title>Part-Time Superhero</title>
    <desc>Part-Time Superhero</desc>
  </programme>
  <programme start="20260708023000 +0000" stop="20260708030000 +0000" channel="airy-536">
    <title>Gimmer 2</title>
    <desc>Gimmer 2</desc>
  </programme>
  <programme start="20260708030000 +0000" stop="20260708033000 +0000" channel="airy-536">
    <title>Wo ist Worrawit</title>
    <desc>Wo ist Worrawit</desc>
  </programme>
  <programme start="20260708033000 +0000" stop="20260708040000 +0000" channel="airy-536">
    <title>Compassion In Thailand</title>
    <desc>Compassion In Thailand</desc>
  </programme>
  <programme start="20260708040000 +0000" stop="20260708043000 +0000" channel="airy-536">
    <title>Half an Angel 2002</title>
    <desc>Half an Angel 2002</desc>
  </programme>
  <programme start="20260708043000 +0000" stop="20260708050000 +0000" channel="airy-536">
    <title>Taxi Karaoke - Short Film</title>
    <desc>Taxi Karaoke - Short Film</desc>
  </programme>
  <programme start="20260708050000 +0000" stop="20260708053000 +0000" channel="airy-536">
    <title>The Tsunami in Thailand 2004</title>
    <desc>The Tsunami in Thailand 2004</desc>
  </programme>
  <programme start="20260708053000 +0000" stop="20260708060000 +0000" channel="airy-536">
    <title>Undocumented</title>
    <desc>Undocumented</desc>
  </programme>
  <programme start="20260708060000 +0000" stop="20260708063000 +0000" channel="airy-536">
    <title>Lets Go Thailand Sights and Sounds Ep 003</title>
    <desc>Lets Go Thailand Sights and Sounds Ep 003</desc>
  </programme>
  <programme start="20260708063000 +0000" stop="20260708070000 +0000" channel="airy-536">
    <title>Lets Go Thailand The Long Way to Bangkok Ep 016</title>
    <desc>Lets Go Thailand The Long Way to Bangkok Ep 016</desc>
  </programme>
  <programme start="20260708070000 +0000" stop="20260708080000 +0000" channel="airy-536">
    <title>Hockey Night in Thailand</title>
    <desc>Hockey Night in Thailand</desc>
  </programme>
  <channel id="airy-606">
    <display-name>Cinema Star</display-name>
    <icon src="" />
  </channel>
  <programme start="20260708000000 +0000" stop="20260708003000 +0000" channel="airy-606">
    <title>Snake In The Eagles Shadow</title>
    <desc>Snake In The Eagles Shadow</desc>
  </programme>
  <programme start="20260708003000 +0000" stop="20260708010000 +0000" channel="airy-606">
    <title>Filler</title>
    <desc>Filler</desc>
  </programme>
  <programme start="20260708010000 +0000" stop="20260708023000 +0000" channel="airy-606">
    <title>Satans Triangle</title>
    <desc>A mysterious woman is the sole survivor of a boat wreck caused by a sudden terrible storm off the coast of Florida</desc>
  </programme>
  <programme start="20260708023000 +0000" stop="20260708040000 +0000" channel="airy-606">
    <title>The Strange and Deadly Occurance</title>
    <desc>Something or someone haunts a couples Robert Stack Vera Miles new home in the country</desc>
  </programme>
  <programme start="20260708040000 +0000" stop="20260708053000 +0000" channel="airy-606">
    <title>The Horror at 37000 Feet</title>
    <desc>An invisible demon in the cargo hold of a jet airliner terrorizes the passengers</desc>
  </programme>
  <programme start="20260708053000 +0000" stop="20260708070000 +0000" channel="airy-606">
    <title>Night of the Zombies</title>
    <desc>Investigators search for soldiers missing bodies and hear unbelievable rumors about zombies Dismissing those rumors they set out to investigate After two men are found dead CIA special-agent Nick Monroe is sent to flush out what are suspected to be deserters from the old US Army Chemical Corps unit Nicks ruthless investigation uncovers a ghoulish plot of world domination but first he must escape the horror that does not want to be known yet!</desc>
  </programme>
  <programme start="20260708070000 +0000" stop="20260708080000 +0000" channel="airy-606">
    <title>Invincible Super Chan</title>
    <desc>Invincible Super Chan</desc>
  </programme>
  <channel id="airy-629">
    <display-name>Big Cinema</display-name>
    <icon src="" />
  </channel>
  <programme start="20260708000000 +0000" stop="20260708010000 +0000" channel="airy-629">
    <title>The Incredible Hulk Returns</title>
    <desc>Hopefully on the verge of curing his Hulk condition Banner meets his colleague Don Blake who is mystically linked to a Viking warrior Thor</desc>
  </programme>
  <programme start="20260708010000 +0000" stop="20260708030000 +0000" channel="airy-629">
    <title>Firewalker</title>
    <desc>Two seasoned adventurers recruited by a seemingly psychic woman with a treasure map go on an adventure to recover a horde of gold belonging to an ancient being called the Firewalker</desc>
  </programme>
  <programme start="20260708030000 +0000" stop="20260708043000 +0000" channel="airy-629">
    <title>Bionic Ever After</title>
    <desc>Steve Austin and Jaime Summers are about to get married However before they can something is happening to Jaime It seems like her bionics are failing and no one knows whats wrong with her It seems that someone has been doing something to her who and why At the same time an old friend of Steves is being held prisoner by some terrorists and Steve needing to take his mind off Jaime offers to go and help</desc>
  </programme>
  <programme start="20260708043000 +0000" stop="20260708063000 +0000" channel="airy-629">
    <title>American Flyers</title>
    <desc>Marcus takes his kid brother David with him for a physical test and a brain scan suspecting cerebral aneurysm like their dad died of They head off on bikes for the big Rockies bike race with Marcus Sarah driving the van</desc>
  </programme>
  <programme start="20260708063000 +0000" stop="20260708070000 +0000" channel="airy-629">
    <title>Filler</title>
    <desc>Filler</desc>
  </programme>
  <programme start="20260708070000 +0000" stop="20260708080000 +0000" channel="airy-629">
    <title>The Gladiator</title>
    <desc>A homicidal maniac is on the loose in Los Angeles killing motorists at random with his death car After losing his brother Jeff to the twisted assassin known as Skull Rick Benton takes it upon himself to hunt down the reckless drivers that fill the streets at night Being a master mechanic Rick spends his time converting his pick-up truck into an armed and dangerous vehicle With speed to take on the fastest car and strength to make sure in a one-on-one situation he will be the only survivor The cops soon find out about the vigilante known only as the Gladiator and do all they can to catch him before his citizens arrests go one step too far </desc>
  </programme>
  <channel id="airy-625">
    <display-name>Moviezone</display-name>
    <icon src="" />
  </channel>
  <programme start="20260708000000 +0000" stop="20260708020000 +0000" channel="airy-625">
    <title>Jaws of Satan</title>
    <desc>A preacher whose ancestors were cursed by Druids battles Satan who has taken the form of a huge snake</desc>
  </programme>
  <programme start="20260708020000 +0000" stop="20260708030000 +0000" channel="airy-625">
    <title>Fredy 112</title>
    <desc>Fredy 112</desc>
  </programme>
  <programme start="20260708030000 +0000" stop="20260708033000 +0000" channel="airy-625">
    <title>Tales from the Crypt </title>
    <desc>After the death penalty is abolished an executioner continues his former job through freelancing</desc>
  </programme>
  <programme start="20260708033000 +0000" stop="20260708040000 +0000" channel="airy-625">
    <title>Tales from the Crypt </title>
    <desc>A greedy woman makes the mistake of murdering her husband while an escaped mental patient dressed in a Santa Claus outfit is on the loose</desc>
  </programme>
  <programme start="20260708040000 +0000" stop="20260708043000 +0000" channel="airy-625">
    <title>The Hitchhiker </title>
    <desc>A sculptor uses a drifter and his own abused girlfriend to recreate a murdersuicide</desc>
  </programme>
  <programme start="20260708043000 +0000" stop="20260708050000 +0000" channel="airy-625">
    <title>The Hitchhiker </title>
    <desc>Smarmy and opportunistic reality TV show host Jerry Rulac does an expose on the wild punk nightclub scene for the latest segment of his television program Why Are You Here Jerry uncovers more than he bargained for when he decides to focus on troubled wealthy party girl Donette and her unpredictable gaggle of scary friends</desc>
  </programme>
  <programme start="20260708050000 +0000" stop="20260708053000 +0000" channel="airy-625">
    <title>Werewolf</title>
    <desc>Eric confronts the werewolf Nicholas Remy and discovers that he is more formidable an opponent than Skorzeny ever was</desc>
  </programme>
  <programme start="20260708053000 +0000" stop="20260708060000 +0000" channel="airy-625">
    <title>Werewolf</title>
    <desc>Eric comes to the aid of a blind woman with a talent for trick shooting he meets while working at a carnival when he learns that her fiancé plans on killing her for the insurance money</desc>
  </programme>
  <programme start="20260708060000 +0000" stop="20260708070000 +0000" channel="airy-625">
    <title>Forever Knight </title>
    <desc>A succession of murders lead Nick and Schanke to suspect the villain is hunting the citys most dangerous criminals for sport</desc>
  </programme>
  <programme start="20260708070000 +0000" stop="20260708080000 +0000" channel="airy-625">
    <title>Friday 13th the Series </title>
    <desc>Ryan and Micki search for a cursed mulcher which is the murder weapon of choice for a gardeners assistant</desc>
  </programme>
  <channel id="airy-650">
    <display-name>Scare O Ween</display-name>
    <icon src="" />
  </channel>
  <programme start="20260708000000 +0000" stop="20260708010000 +0000" channel="airy-650">
    <title>The Strange and Deadly Occurance</title>
    <desc>Something or someone haunts a couples Robert Stack Vera Miles new home in the country</desc>
  </programme>
  <programme start="20260708010000 +0000" stop="20260708023000 +0000" channel="airy-650">
    <title>Satans Triangle</title>
    <desc>A mysterious woman is the sole survivor of a boat wreck caused by a sudden terrible storm off the coast of Florida</desc>
  </programme>
  <programme start="20260708023000 +0000" stop="20260708040000 +0000" channel="airy-650">
    <title>The Strange and Deadly Occurance</title>
    <desc>Something or someone haunts a couples Robert Stack Vera Miles new home in the country</desc>
  </programme>
  <programme start="20260708040000 +0000" stop="20260708053000 +0000" channel="airy-650">
    <title>The Horror at 37000 Feet</title>
    <desc>An invisible demon in the cargo hold of a jet airliner terrorizes the passengers</desc>
  </programme>
  <programme start="20260708053000 +0000" stop="20260708070000 +0000" channel="airy-650">
    <title>Satans Triangle</title>
    <desc>A mysterious woman is the sole survivor of a boat wreck caused by a sudden terrible storm off the coast of Florida</desc>
  </programme>
  <programme start="20260708070000 +0000" stop="20260708080000 +0000" channel="airy-650">
    <title>The Horror at 37000 Feet</title>
    <desc>An invisible demon in the cargo hold of a jet airliner terrorizes the passengers</desc>
  </programme>
  <channel id="airy-405">
    <display-name>Fishing Offshore</display-name>
    <icon src="" />
  </channel>
  <programme start="20260708000000 +0000" stop="20260708010000 +0000" channel="airy-405">
    <title>Darcizzle</title>
    <desc>Searching for Ocean Treasure Underwater! Found a RARE TROPHY! RIVER MONSTERS! Epic Bridge Battles with Huge Predator Fish (South Florida) Fishing Girl Catches M"</desc>
  </programme>
  <programme start="20260708010000 +0000" stop="20260708020000 +0000" channel="airy-405">
    <title>Darcizzle</title>
    <desc>Massive Florida Keys African Pompano! (catch andamp;amp; cook) RIPPING Fish Off Pilings! Bonefish, Sheepshead andamp;amp; Tripletail Catch andamp;amp; Cook Flor"</desc>
  </programme>
  <programme start="20260708020000 +0000" stop="20260708030000 +0000" channel="airy-405">
    <title>Darcizzle</title>
    <desc>NEW $3,000 Combo Fishing 1000andamp;#39; DEEP! Catching Weird Fish EVERY Time Trophy Fish Caught! NEW Florida Pompano Catch andamp;amp; Cook SHARK attacks fishi"</desc>
  </programme>
  <programme start="20260708030000 +0000" stop="20260708040000 +0000" channel="airy-405">
    <title>Darcizzle</title>
    <desc>We're Back! Florida Offshore Fishing Mullet Run Inshore Saltwater Fishing for Snook in Stuart, Florida RELEASE or NO Release? The MAJESTIC ATLANTIC SAILFISH Cha"</desc>
  </programme>
  <programme start="20260708040000 +0000" stop="20260708050000 +0000" channel="airy-405">
    <title>Darcizzle</title>
    <desc>UNEXPECTED Battle with PROHIBITED SHARK SPECIES! On TINY short ROD! Florida Lobster: HOW TO Catch, Clean andamp; Cook! Barefoot Shark Fishing feat. DJI Phantom "</desc>
  </programme>
  <programme start="20260708050000 +0000" stop="20260708060000 +0000" channel="airy-405">
    <title>Darcizzle</title>
    <desc>Fishing the Florida Keys, Marathon; Day One...blown tires andamp; good food I Catch andamp;amp; Cook the Worldandamp;#39;s Thinnest Fish! Fly Fishing in the Bon"</desc>
  </programme>
  <programme start="20260708060000 +0000" stop="20260708070000 +0000" channel="airy-405">
    <title>Darcizzle</title>
    <desc>BIG GROUPERS Offshore SW Florida Fishing with Soldiers Tournament FINAL Goodbye: U.S. Marine Corps RECRUIT Heads to Parris Island! UNEXPECTED Massive Florida Ke"</desc>
  </programme>
  <programme start="20260708070000 +0000" stop="20260708080000 +0000" channel="airy-405">
    <title>Darcizzle</title>
    <desc>Monster Vermillion (Catch Clean Cook) BBQ Snapper on the HALF SHELL! Unexpected GIANT Surprise Catch Deep Sea Wreck Fishing! Atlantic Sailfish in Stuart, Florid"</desc>
  </programme>
  <channel id="airy-443">
    <display-name>Hard Knocks</display-name>
    <icon src="" />
  </channel>
  <programme start="20260708000000 +0000" stop="20260708000524 +0000" channel="airy-443">
    <title>Hard Knocks</title>
    <desc>The Premier MMA promotion, Telecast live across the globe Showcasing some of the worlds best MMA athletes.</desc>
  </programme>
  <programme start="20260708000524 +0000" stop="20260708000916 +0000" channel="airy-443">
    <title>Hard Knocks</title>
    <desc>Anis Dada v. Scott Turner</desc>
  </programme>
  <programme start="20260708000916 +0000" stop="20260708003526 +0000" channel="airy-443">
    <title>Hard Knocks</title>
    <desc>Out of the Cage reveals the private thoughts and emotions of an MMA fighter, the ambition that drives them and how they are affected when encountering defeat or facing triumph. Featuring Leo Pla at HK50</desc>
  </programme>
  <programme start="20260708003526 +0000" stop="20260708013324 +0000" channel="airy-443">
    <title>HK Best Of's - Submissions Fall 2014 - Episode 2 NEW</title>
    <desc>HK Best Of's - Submissions Fall 2014 - Episode 2 NEW</desc>
  </programme>
  <programme start="20260708013324 +0000" stop="20260708015039 +0000" channel="airy-443">
    <title>Hard Knocks</title>
    <desc>Main Event - Sheldon Gaines v. Nate Smandych</desc>
  </programme>
  <programme start="20260708015039 +0000" stop="20260708020733 +0000" channel="airy-443">
    <title>Hard Knocks</title>
    <desc>Professional and Amateur fighters from across North America battle it out in Hard Knocks' cage. Mike Goehr v. Barrett Thompson.</desc>
  </programme>
  <programme start="20260708020733 +0000" stop="20260708020809 +0000" channel="airy-443">
    <title>Hard Knocks</title>
    <desc>Chris Smith v. Gareth Millar</desc>
  </programme>
  <programme start="20260708020809 +0000" stop="20260708020837 +0000" channel="airy-443">
    <title>Hard Knocks</title>
    <desc>The Premier MMA promotion, Telecast live across the globe Showcasing some of the worlds best MMA athletes.</desc>
  </programme>
  <programme start="20260708020837 +0000" stop="20260708021037 +0000" channel="airy-443">
    <title>Hard Knocks</title>
    <desc>The Premier MMA promotion, Telecast live across the globe Showcasing some of the worlds best MMA athletes.</desc>
  </programme>
  <programme start="20260708021037 +0000" stop="20260708021134 +0000" channel="airy-443">
    <title>Hard Knocks</title>
    <desc>The Premier MMA promotion, Telecast live across the globe Showcasing some of the worlds best MMA athletes.</desc>
  </programme>
  <programme start="20260708021134 +0000" stop="20260708021302 +0000" channel="airy-443">
    <title>Hard Knocks</title>
    <desc>The Premier MMA promotion, Telecast live across the globe Showcasing some of the worlds best MMA athletes.</desc>
  </programme>
  <programme start="20260708021302 +0000" stop="20260708031032 +0000" channel="airy-443">
    <title>Hard Knocks</title>
    <desc>The School of Hard Knocks 32 filmed at the Century Casino in Calgary. Professional and Amateur fighters from across North America battle it out in the cage. Anton Tokarchuck vs. Bryce Berry; Matt Kristufek vs. Elliot Duff.</desc>
  </programme>
  <programme start="20260708031032 +0000" stop="20260708031109 +0000" channel="airy-443">
    <title>Hard Knocks</title>
    <desc>Dalgiev Khamzat v. Dragan Pesic</desc>
  </programme>
  <programme start="20260708031109 +0000" stop="20260708040842 +0000" channel="airy-443">
    <title>Hard Knocks</title>
    <desc>The School of Hard Knocks 32 filmed at the Century Casino in Calgary. Professional and Amateur fighters from across North America battle it out in the cage. Eric Schmit vs. Andrew Vandervelden; Daniel Garcia vs. Keegan Oliver.</desc>
  </programme>
  <programme start="20260708040842 +0000" stop="20260708042255 +0000" channel="airy-443">
    <title>Hard Knocks</title>
    <desc>Hicham Achalhi v. Andre Schmeling</desc>
  </programme>
  <programme start="20260708042255 +0000" stop="20260708045159 +0000" channel="airy-443">
    <title>Hard Knocks</title>
    <desc>Alexey Kunchenko v. Maxim Grabovich</desc>
  </programme>
  <programme start="20260708045159 +0000" stop="20260708050622 +0000" channel="airy-443">
    <title>Hard Knocks</title>
    <desc>Khadija Charradi v. Essilia Wurms</desc>
  </programme>
  <programme start="20260708050622 +0000" stop="20260708050822 +0000" channel="airy-443">
    <title>Hard Knocks</title>
    <desc>The Premier MMA promotion, Telecast live across the globe Showcasing some of the worlds best MMA athletes.</desc>
  </programme>
  <programme start="20260708050822 +0000" stop="20260708053621 +0000" channel="airy-443">
    <title>Hard Knocks</title>
    <desc>The Premier MMA promotion, Telecast live across the globe Showcasing some of the worlds best MMA athletes.</desc>
  </programme>
  <programme start="20260708053621 +0000" stop="20260708062347 +0000" channel="airy-443">
    <title>Hard Knocks</title>
    <desc>The Premier MMA promotion, Telecast live across the globe Showcasing some of the worlds best MMA athletes.</desc>
  </programme>
  <programme start="20260708062347 +0000" stop="20260708063533 +0000" channel="airy-443">
    <title>Hard Knocks</title>
    <desc>Mike Yurko v. Pardeep Sooch</desc>
  </programme>
  <programme start="20260708063533 +0000" stop="20260708064635 +0000" channel="airy-443">
    <title>Hard Knocks</title>
    <desc>Live from Hollywood, CA on January 24, 2019, Karate Combat: Hollywood kicks off Karate Combat's sophomore season. Held at the Avalon, the former Hollywood Palace building, near the famous intersection of Hollywood and Vine. Ilies Mardhi v. Daniel Viveros.</desc>
  </programme>
  <programme start="20260708064635 +0000" stop="20260708070400 +0000" channel="airy-443">
    <title>Hard Knocks</title>
    <desc>Xavier Sedras v. Jefferson George</desc>
  </programme>
  <programme start="20260708070400 +0000" stop="20260708071649 +0000" channel="airy-443">
    <title>Hard Knocks</title>
    <desc>Professional and Amateur fighters from across North America battle it out in Hard Knocks' cage. Jerad Meyer v. Zach Snyder.</desc>
  </programme>
  <programme start="20260708071649 +0000" stop="20260708073401 +0000" channel="airy-443">
    <title>Hard Knocks</title>
    <desc>Hard Knocks</desc>
  </programme>
  <programme start="20260708073401 +0000" stop="20260708074504 +0000" channel="airy-443">
    <title>Hard Knocks</title>
    <desc>Live from Hollywood, CA on January 24, 2019, Karate Combat: Hollywood kicks off Karate Combat's sophomore season. Held at the Avalon, the former Hollywood Palace building, near the famous intersection of Hollywood and Vine. Elhadji Ndour v. Calum Robb.</desc>
  </programme>
  <programme start="20260708074504 +0000" stop="20260708075911 +0000" channel="airy-443">
    <title>Hard Knocks</title>
    <desc>Kirsty Davis v. Jess Offermans</desc>
  </programme>
  <programme start="20260708075911 +0000" stop="20260708080000 +0000" channel="airy-443">
    <title>Hard Knocks</title>
    <desc>Professional and Amateur fighters from across North America battle it out in Hard Knocks' cage. Tyrone Halkett v. Travis Favel.</desc>
  </programme>
  <channel id="airy-653">
    <display-name>Mob Candy Magazine</display-name>
    <icon src="" />
  </channel>
  <programme start="20260708000000 +0000" stop="20260708010000 +0000" channel="airy-653">
    <title>MC MamaJones Part2</title>
    <desc>MC MamaJones Part2</desc>
  </programme>
  <programme start="20260708010000 +0000" stop="20260708020000 +0000" channel="airy-653">
    <title>MC MamaJones Part3</title>
    <desc>MC MamaJones Part3</desc>
  </programme>
  <programme start="20260708020000 +0000" stop="20260708030000 +0000" channel="airy-653">
    <title>MC MamaJones Part1</title>
    <desc>MC MamaJones Part1</desc>
  </programme>
  <programme start="20260708030000 +0000" stop="20260708033000 +0000" channel="airy-653">
    <title>MC renee</title>
    <desc>MC renee</desc>
  </programme>
  <programme start="20260708033000 +0000" stop="20260708040000 +0000" channel="airy-653">
    <title>MC renee</title>
    <desc>MC renee</desc>
  </programme>
  <programme start="20260708040000 +0000" stop="20260708043000 +0000" channel="airy-653">
    <title>Episode 2–Mob Candy</title>
    <desc>Episode 2–Mob Candy</desc>
  </programme>
  <programme start="20260708043000 +0000" stop="20260708053000 +0000" channel="airy-653">
    <title>David_Zuker_Episode_7_Mob_Candy_Artie_Pasquale_33AA_33BB_33CC_33DD_33EE_17K_48Sample_R100</title>
    <desc>David_Zuker_Episode_7_Mob_Candy_Artie_Pasquale_33AA_33BB_33CC_33DD_33EE_17K_48Sample_R100</desc>
  </programme>
  <programme start="20260708053000 +0000" stop="20260708060000 +0000" channel="airy-653">
    <title>Episode 1–Mob Candy</title>
    <desc>Episode 1–Mob Candy</desc>
  </programme>
  <programme start="20260708060000 +0000" stop="20260708070000 +0000" channel="airy-653">
    <title>David_Zuker_Episode_8_Mob_Candy_Louie_Hubella_33FF_33GG_33HH_33II_33JJ_33KK_17K_48Sample_R100</title>
    <desc>David_Zuker_Episode_8_Mob_Candy_Louie_Hubella_33FF_33GG_33HH_33II_33JJ_33KK_17K_48Sample_R100</desc>
  </programme>
  <programme start="20260708070000 +0000" stop="20260708080000 +0000" channel="airy-653">
    <title>MC renee part2 nomark</title>
    <desc>MC renee part2 nomark</desc>
  </programme>
  <channel id="airy-505">
    <display-name>The Sherard Show</display-name>
    <icon src="" />
  </channel>
  <programme start="20260708000000 +0000" stop="20260708003000 +0000" channel="airy-505">
    <title>The DC Glenn Exclusive Interview</title>
    <desc>Meet the man who created a 90s anthem that set the trend for Hip Hop Music today</desc>
  </programme>
  <programme start="20260708003000 +0000" stop="20260708013000 +0000" channel="airy-505">
    <title>The April Taylor Interview</title>
    <desc>Join me as I sit down with the lady whose upcoming celebrity tell all book will blow your mind Meet the lovely Ms April Taylor</desc>
  </programme>
  <programme start="20260708013000 +0000" stop="20260708023000 +0000" channel="airy-505">
    <title>The Cynda Williams Interview</title>
    <desc>Meet the lady who became a star in the 1990s hit movie Mo Betta Blues Hear how selling herself out to become rich was and still isnt an option</desc>
  </programme>
  <programme start="20260708023000 +0000" stop="20260708040000 +0000" channel="airy-505">
    <title>The Chico Brown Exclusive Interview</title>
    <desc>From being the Co-defendant to Rick Ross to becoming a successful film maker Chico Brown stops by the show to set the record straight</desc>
  </programme>
  <programme start="20260708040000 +0000" stop="20260708053000 +0000" channel="airy-505">
    <title>The Sean Kanan Interview</title>
    <desc>Sherard sits down with Cobra Kai star Sean Kanan aka Mr Mike Barnes Learn how the success of Karate Kid 3 and Cobra Kai still amazes him</desc>
  </programme>
  <programme start="20260708053000 +0000" stop="20260708063000 +0000" channel="airy-505">
    <title>The Jaxx Kellerman Interview</title>
    <desc>Meet this young lady who writes and performs with a real chip on her shoulder Jaxx Kellerman on the Sherard Show</desc>
  </programme>
  <programme start="20260708063000 +0000" stop="20260708070000 +0000" channel="airy-505">
    <title>The Tim Hayes Interview</title>
    <desc>Sherard sits down with the man who has turn comedy into an art</desc>
  </programme>
  <programme start="20260708070000 +0000" stop="20260708080000 +0000" channel="airy-505">
    <title>The DC Glenn Exclusive Interview</title>
    <desc>Meet the man who created a 90s anthem that set the trend for Hip Hop Music today</desc>
  </programme>
  <channel id="airy-585">
    <display-name>Nashville Country TV</display-name>
    <icon src="" />
  </channel>
  <programme start="20260708000000 +0000" stop="20260708010000 +0000" channel="airy-585">
    <title>Country Music</title>
    <desc>Country Music Video Mix</desc>
  </programme>
  <programme start="20260708010000 +0000" stop="20260708023000 +0000" channel="airy-585">
    <title>Country Music</title>
    <desc>Country Music Video Mix</desc>
  </programme>
  <programme start="20260708023000 +0000" stop="20260708033000 +0000" channel="airy-585">
    <title>Country Music</title>
    <desc>Country Music Video Mix</desc>
  </programme>
  <programme start="20260708033000 +0000" stop="20260708043000 +0000" channel="airy-585">
    <title>Country Music</title>
    <desc>Country Music Video Mix</desc>
  </programme>
  <programme start="20260708043000 +0000" stop="20260708053000 +0000" channel="airy-585">
    <title>Country Music</title>
    <desc>Country Music Video Mix</desc>
  </programme>
  <programme start="20260708053000 +0000" stop="20260708063000 +0000" channel="airy-585">
    <title>Country Music</title>
    <desc>Country Music Video Mix</desc>
  </programme>
  <programme start="20260708063000 +0000" stop="20260708070000 +0000" channel="airy-585">
    <title>Filler</title>
    <desc>Filler</desc>
  </programme>
  <programme start="20260708070000 +0000" stop="20260708080000 +0000" channel="airy-585">
    <title>Country Music</title>
    <desc>Country Music Video Mix</desc>
  </programme>
  <channel id="airy-556">
    <display-name>My Jam Music TV</display-name>
    <icon src="" />
  </channel>
  <programme start="20260708000000 +0000" stop="20260708003000 +0000" channel="airy-556">
    <title>Cowboys Wear Stetsons – Duncan Daniels [Official Video]</title>
    <desc>Cowboys Wear Stetsons – Duncan Daniels [Official Video]</desc>
  </programme>
  <programme start="20260708003000 +0000" stop="20260708010000 +0000" channel="airy-556">
    <title>Water Tower Will Carter Band</title>
    <desc>Water Tower Will Carter Band</desc>
  </programme>
  <programme start="20260708010000 +0000" stop="20260708013000 +0000" channel="airy-556">
    <title>Orphan Train Official Video Trey Hensley Rob Ickes Tammy Rogers</title>
    <desc>Orphan Train Official Video Trey Hensley Rob Ickes Tammy Rogers</desc>
  </programme>
  <programme start="20260708013000 +0000" stop="20260708020000 +0000" channel="airy-556">
    <title>MICHAEL LYNNE THREE CHORD DRINKIN SONG OFFICIAL MUSIC VIDEO</title>
    <desc>MICHAEL LYNNE THREE CHORD DRINKIN SONG OFFICIAL MUSIC VIDEO</desc>
  </programme>
  <programme start="20260708020000 +0000" stop="20260708023000 +0000" channel="airy-556">
    <title>Candice Night Unsung Hero</title>
    <desc>Candice Night Unsung Hero</desc>
  </programme>
  <programme start="20260708023000 +0000" stop="20260708030000 +0000" channel="airy-556">
    <title>Forever single Official Music Video The Swansons</title>
    <desc>Forever single Official Music Video The Swansons</desc>
  </programme>
  <programme start="20260708030000 +0000" stop="20260708033000 +0000" channel="airy-556">
    <title>RobinEnglish GiveEmHellKid OfficialMusicVideo</title>
    <desc>RobinEnglish GiveEmHellKid OfficialMusicVideo</desc>
  </programme>
  <programme start="20260708033000 +0000" stop="20260708040000 +0000" channel="airy-556">
    <title>Cant Stop by The Hammond Brothers</title>
    <desc>Cant Stop by The Hammond Brothers</desc>
  </programme>
  <programme start="20260708040000 +0000" stop="20260708043000 +0000" channel="airy-556">
    <title>Laura Sawosko Take My Hand Official Video</title>
    <desc>Laura Sawosko Take My Hand Official Video</desc>
  </programme>
  <programme start="20260708043000 +0000" stop="20260708050000 +0000" channel="airy-556">
    <title>Leon Lewis No Blues In Heaven</title>
    <desc>Leon Lewis No Blues In Heaven</desc>
  </programme>
  <programme start="20260708050000 +0000" stop="20260708053000 +0000" channel="airy-556">
    <title>God Knows Where Official Music Video</title>
    <desc>God Knows Where Official Music Video</desc>
  </programme>
  <programme start="20260708053000 +0000" stop="20260708060000 +0000" channel="airy-556">
    <title>RITAS SONG</title>
    <desc>RITAS SONG</desc>
  </programme>
  <programme start="20260708060000 +0000" stop="20260708063000 +0000" channel="airy-556">
    <title>Dead Man Walking ft Leland Chapman Official Music Video Kevin Palmer</title>
    <desc>Dead Man Walking ft Leland Chapman Official Music Video Kevin Palmer</desc>
  </programme>
  <programme start="20260708063000 +0000" stop="20260708070000 +0000" channel="airy-556">
    <title>Soul Circus Cowboys feat Eddy Raven I Got Mexico</title>
    <desc>Soul Circus Cowboys feat Eddy Raven I Got Mexico</desc>
  </programme>
  <programme start="20260708070000 +0000" stop="20260708073000 +0000" channel="airy-556">
    <title>YEAR OF THE SQRAT ATTACK</title>
    <desc>YEAR OF THE SQRAT ATTACK</desc>
  </programme>
  <programme start="20260708073000 +0000" stop="20260708080000 +0000" channel="airy-556">
    <title>Captains_Of_Entropy_The_Flea</title>
    <desc>Captains_Of_Entropy_The_Flea</desc>
  </programme>
  <channel id="airy-550">
    <display-name>Sidewalks TV</display-name>
    <icon src="" />
  </channel>
  <programme start="20260708000000 +0000" stop="20260708010000 +0000" channel="airy-550">
    <title>Sidewalks Interviews</title>
    <desc>: Roma Downey (2017) : Jack McBrayer : Viggo Mortensen : Ellen Page  Ian Daniel (Gaycation) : Connie Britton : Doris Roberts (2005)"</desc>
  </programme>
  <programme start="20260708010000 +0000" stop="20260708020000 +0000" channel="airy-550">
    <title>Sidewalks Interviews</title>
    <desc>: Dee Bradley Baker and Rachael MacFarlane (American Dad!) : A.F. Steadman (Skandar and the Unicorn Thief) : Harmon Killebrew : Katie Armiger (part 2 of three) "</desc>
  </programme>
  <programme start="20260708020000 +0000" stop="20260708030000 +0000" channel="airy-550">
    <title>Other Sidewalks Stories</title>
    <desc>Feature: UCLA Meteorite Collection Rogue Heroes Feature (TV version) Actor's Spotlight - Evelyn Arreaga Sidewalks Sizzle Reel (2019) FOB Kitchen with Chef Janic"</desc>
  </programme>
  <programme start="20260708030000 +0000" stop="20260708040000 +0000" channel="airy-550">
    <title>Sidewalks Interviews</title>
    <desc>: Josh Holloway and Sarah Wayne Callies : Josh Gates : Wilmer Valderrama (September 2022) : Kevin Daniels and Kevin Bigley (Sirens) : Victoria Kann"</desc>
  </programme>
  <programme start="20260708040000 +0000" stop="20260708050000 +0000" channel="airy-550">
    <title>Sidewalks Interviews</title>
    <desc>: Harry Connick, Jr. : David Alan Grier : Logan Lerman and Richard Lanni (Sgt Stubby) : Russell Curry and Hunter Deno (Power Rangers Dino Fury) : Hugh Hefner (2"</desc>
  </programme>
  <programme start="20260708050000 +0000" stop="20260708060000 +0000" channel="airy-550">
    <title>Sidewalks Interviews</title>
    <desc>: Hunter Hayes (TV Version) : The Miz : Katie Armiger (part 3 of three) : Max Grod chik  Aron Eisenberg (Star Trek: DS9)"</desc>
  </programme>
  <programme start="20260708060000 +0000" stop="20260708070000 +0000" channel="airy-550">
    <title>Newest Sidewalks Episode</title>
    <desc>: Lauren Ambrose and Toby Kebbell (Servant) : Jeff Wahlberg : Joe Morton and Tracey Moore (Inside the Black Box) : Andy Williams (2009) : The Lockets (Jenny  As"</desc>
  </programme>
  <programme start="20260708070000 +0000" stop="20260708080000 +0000" channel="airy-550">
    <title>Sidewalks Interviews</title>
    <desc>: Jerry Mathers : Adeline Gray : John Singleton and Danielle Monand#233; Truitt (Rebel) : Dirk Benedict"</desc>
  </programme>
  <channel id="airy-551">
    <display-name>The Beach Show</display-name>
    <icon src="" />
  </channel>
  <programme start="20260708000000 +0000" stop="20260708010000 +0000" channel="airy-551">
    <title>Beachy-Beach</title>
    <desc>Waterfront Deer Point Lake Living in Panama City Beach andamp;amp; Beyond! West End on Panama City BeachLiving in Panama City Beach andamp;amp; Beyond! West End"</desc>
  </programme>
  <programme start="20260708010000 +0000" stop="20260708020000 +0000" channel="airy-551">
    <title>Beachy-Beach</title>
    <desc>Southwind Condo Living in Panama City Beach andamp;amp; Beyond! Horizon South 21C CondoLiving in Panama City Beach andamp;amp; Beyond! Laguna Beach across from "</desc>
  </programme>
  <programme start="20260708020000 +0000" stop="20260708030000 +0000" channel="airy-551">
    <title>Beachy-Beach</title>
    <desc>West End DuplexLiving in Panama City Beach andamp;amp; Beyond! Callaway CornersLiving in Panama City Beach andamp;amp; Beyond! Panama City Beach Great Neighborh"</desc>
  </programme>
  <programme start="20260708030000 +0000" stop="20260708040000 +0000" channel="airy-551">
    <title>Beachy-Beach</title>
    <desc>Luxury with a Pool Panama City BeachLiving in Panama City Beach andamp;amp; Beyond! West End Condo on Panama City BeachLiving in Panama City Beach andamp;amp; B"</desc>
  </programme>
  <programme start="20260708040000 +0000" stop="20260708050000 +0000" channel="airy-551">
    <title>Beachy-Beach</title>
    <desc>Bay Point WATERFRONTLiving in Panama City Beach andamp;amp; Beyond! Bid-A-Wee NeighborhoodLiving in Panama City Beach andamp;amp; Beyond! 115 Malaga Pl Beachy B"</desc>
  </programme>
  <programme start="20260708050000 +0000" stop="20260708060000 +0000" channel="airy-551">
    <title>Beachy-Beach</title>
    <desc>Colony ClubLiving in Panama City Beach andamp;amp; Beyond! iving in Panama City Beach and Beyond!  The Wabi Sabis - Open House - Bathroom Session Panama City ~ "</desc>
  </programme>
  <programme start="20260708060000 +0000" stop="20260708070000 +0000" channel="airy-551">
    <title>Beachy-Beach</title>
    <desc>Brad Stephens andamp;amp; Sunjammers Support GLAM JAM 16 - Beachy Beach Wild Heron Living in Panama City Beach andamp; Beyond!  Bryan Taylor - Glam Jam 16 Celeb"</desc>
  </programme>
  <programme start="20260708070000 +0000" stop="20260708080000 +0000" channel="airy-551">
    <title>Beachy-Beach</title>
    <desc>Origins CondoLiving in Panama City Beach andamp;amp; Beyond! Inn at Blue Mountain - GULF FRONTLiving in Panama City Beach andamp;amp; Beyond! Laguna Beach Cotta"</desc>
  </programme>
  <channel id="airy-656">
    <display-name>Now Media Spanish</display-name>
    <icon src="" />
  </channel>
  <programme start="20260708000000 +0000" stop="20260708010000 +0000" channel="airy-656">
    <title>LAS NOTICIAS CON ALEJANDRO CACHO</title>
    <desc>Las Noticias con Alejandro Cacho · ¡México es reconocido con el Premio Princesa de Asturias! · Las noticias con Alejandro Cacho</desc>
  </programme>
  <programme start="20260708010000 +0000" stop="20260708020000 +0000" channel="airy-656">
    <title>VOZ SHOW 06 30 2026 online</title>
    <desc>VOZ SHOW 06 30 2026 online</desc>
  </programme>
  <programme start="20260708020000 +0000" stop="20260708030000 +0000" channel="airy-656">
    <title>NOTICIAS CON SOFÍA VILLALOBOS</title>
    <desc>Bloomberg</desc>
  </programme>
  <programme start="20260708030000 +0000" stop="20260708040000 +0000" channel="airy-656">
    <title>AL CIERRE</title>
    <desc>bloomberg</desc>
  </programme>
  <programme start="20260708040000 +0000" stop="20260708050000 +0000" channel="airy-656">
    <title>CON ORTEGA A LAS 10</title>
    <desc>Bloomberg</desc>
  </programme>
  <programme start="20260708050000 +0000" stop="20260708053000 +0000" channel="airy-656">
    <title>BEE MIRACLE</title>
    <desc>BEE MIRACLE</desc>
  </programme>
  <programme start="20260708053000 +0000" stop="20260708060000 +0000" channel="airy-656">
    <title>SPANISH TAX HELP LONG FORM</title>
    <desc>SPANISH TAX HELP LONG FORM</desc>
  </programme>
  <programme start="20260708060000 +0000" stop="20260708063000 +0000" channel="airy-656">
    <title>VUELOYMAS LONG FORM</title>
    <desc>VUELOYMAS LONG FORM</desc>
  </programme>
  <programme start="20260708063000 +0000" stop="20260708070000 +0000" channel="airy-656">
    <title>BEE MIRACLE</title>
    <desc>BEE MIRACLE</desc>
  </programme>
  <programme start="20260708070000 +0000" stop="20260708073000 +0000" channel="airy-656">
    <title>SPANISH TAX HELP LONG FORM</title>
    <desc>SPANISH TAX HELP LONG FORM</desc>
  </programme>
  <programme start="20260708073000 +0000" stop="20260708080000 +0000" channel="airy-656">
    <title>VUELOYMAS LONG FORM</title>
    <desc>VUELOYMAS LONG FORM</desc>
  </programme>
  <channel id="airy-657">
    <display-name>Now Media English</display-name>
    <icon src="" />
  </channel>
  <programme start="20260708000000 +0000" stop="20260708010000 +0000" channel="airy-657">
    <title>The Raz Patel Show Kapil</title>
    <desc>The Raz Patel Show Kapil</desc>
  </programme>
  <programme start="20260708010000 +0000" stop="20260708020000 +0000" channel="airy-657">
    <title>Everyday Leaders Unfiltered Raechelle Johnson 4-28-26</title>
    <desc>Everyday Leaders Unfiltered Raechelle Johnson 4-28-26</desc>
  </programme>
  <programme start="20260708020000 +0000" stop="20260708030000 +0000" channel="airy-657">
    <title>ABUNDANT ENERGY STEPHANIE PIERUCCI 6 30 26</title>
    <desc>ABUNDANT ENERGY STEPHANIE PIERUCCI 6 30 26</desc>
  </programme>
  <programme start="20260708030000 +0000" stop="20260708040000 +0000" channel="airy-657">
    <title>DW ENGLISH</title>
    <desc>News off-beat stories and analysis of German and international affairs Dive deeper with our features from Europe and beyond Watch our 247 TV stream</desc>
  </programme>
  <programme start="20260708040000 +0000" stop="20260708043000 +0000" channel="airy-657">
    <title>Jacuzzi Bath Remodel Long Form</title>
    <desc>Jacuzzi Bath Remodel Long Form</desc>
  </programme>
  <programme start="20260708043000 +0000" stop="20260708050000 +0000" channel="airy-657">
    <title>TAX HELP LF 2016</title>
    <desc>TAX HELP LF 2016</desc>
  </programme>
  <programme start="20260708050000 +0000" stop="20260708053000 +0000" channel="airy-657">
    <title>HOME BUYERS airtime</title>
    <desc>HOME BUYERS airtime</desc>
  </programme>
  <programme start="20260708053000 +0000" stop="20260708060000 +0000" channel="airy-657">
    <title>GET HELP NOW</title>
    <desc>GET HELP NOW</desc>
  </programme>
  <programme start="20260708060000 +0000" stop="20260708063000 +0000" channel="airy-657">
    <title>Time Share Exit LF</title>
    <desc>Time Share Exit LF</desc>
  </programme>
  <programme start="20260708063000 +0000" stop="20260708070000 +0000" channel="airy-657">
    <title>CAR SHIELD All Stars V5</title>
    <desc>CAR SHIELD All Stars V5</desc>
  </programme>
  <programme start="20260708070000 +0000" stop="20260708073000 +0000" channel="airy-657">
    <title>LOW COST AIR LONG FORM</title>
    <desc>LOW COST AIR LONG FORM</desc>
  </programme>
  <programme start="20260708073000 +0000" stop="20260708080000 +0000" channel="airy-657">
    <title>Jacuzzi Bath Remodel Long Form</title>
    <desc>Jacuzzi Bath Remodel Long Form</desc>
  </programme>
  <channel id="airy-552">
    <display-name>Georgia Hollywood Review TV</display-name>
    <icon src="" />
  </channel>
  <programme start="20260708000000 +0000" stop="20260708010000 +0000" channel="airy-552">
    <title>Georgia Hollywood Review</title>
    <desc>Chris LeDoux, Founder/Senior VFX Supervisor of Crafty Apes - Georgia Hollywood Review TV Ryan Dennis Interviewing DC the Brain Supreme v3 Whoomp There it is ! M"</desc>
  </programme>
  <programme start="20260708010000 +0000" stop="20260708020000 +0000" channel="airy-552">
    <title>Georgia Hollywood Review</title>
    <desc>Denitra Isler Interview - Georgia Hollywood Review TV WIFTA Gala - Georgia Hollywood Review - Red Carpet Series Wahlburgers - Georgia Hollywood Review TV Georgi"</desc>
  </programme>
  <programme start="20260708020000 +0000" stop="20260708030000 +0000" channel="airy-552">
    <title>Georgia Hollywood Review</title>
    <desc>Alahna Lark - Georgia Hollywood Review TV Kim Leadford andamp; Doris Casap - Georgia Hollywood Review TV - OTT Fest 2019 Stickz Greenz - Georgia Hollywood Revie"</desc>
  </programme>
  <programme start="20260708030000 +0000" stop="20260708040000 +0000" channel="airy-552">
    <title>Georgia Hollywood Review</title>
    <desc>Kim Leadford and Doris Casap - Georgia Hollywood Review TV - OTT Fest 2019 Jason Evans - Georgia Hollywood Review TV Rmy Martin x Usher | #TeamUpForExcellence t"</desc>
  </programme>
  <programme start="20260708040000 +0000" stop="20260708050000 +0000" channel="airy-552">
    <title>Georgia Hollywood Review</title>
    <desc>Atlanta Jewish Film Festival 2020 - Georgia Hollywood Review TV Deborah Riley Draper Interview - Georgia Hollywood Review TV - Miles Neiman - Georgia Film Fund "</desc>
  </programme>
  <programme start="20260708050000 +0000" stop="20260708060000 +0000" channel="airy-552">
    <title>Georgia Hollywood Review</title>
    <desc>Latina Women In Media Atlanta  - GHR Entertainment News Today Georgia Hollywood Review TV - Monica Diter Advertise with the Georgia Hollywood Review Jason Evans"</desc>
  </programme>
  <programme start="20260708060000 +0000" stop="20260708070000 +0000" channel="airy-552">
    <title>Georgia Hollywood Review</title>
    <desc>Cas Sigers Beedles - Georgia Hollywood Review TV Kim Leadford andamp; Doris Casap - Georgia Hollywood Review TV - OTT Fest 2019 Kate Atwood - Georgia Hollywood "</desc>
  </programme>
  <programme start="20260708070000 +0000" stop="20260708080000 +0000" channel="airy-552">
    <title>Georgia Hollywood Review</title>
    <desc>Caitlynn Silvius, Gaffer - Georgia Hollywood Review TV Advertise with the Georgia Hollywood Review Keanu Reeves Plays With Puppies While Answering Fan Questions"</desc>
  </programme>
  <channel id="airy-633">
    <display-name>Kids Net</display-name>
    <icon src="" />
  </channel>
  <programme start="20260708000000 +0000" stop="20260708003000 +0000" channel="airy-633">
    <title>Inspector Gadget</title>
    <desc>Gadget protects armoured cars from Dr Claw</desc>
  </programme>
  <programme start="20260708003000 +0000" stop="20260708010000 +0000" channel="airy-633">
    <title>Inspector Gadget</title>
    <desc>Magic Gadget</desc>
  </programme>
  <programme start="20260708010000 +0000" stop="20260708013000 +0000" channel="airy-633">
    <title>Challenge of the GoBots</title>
    <desc>Cy-Kill escapes from the prison moon to rally his Renegades for an all-out offensive that leaves Turbo mortally damaged</desc>
  </programme>
  <programme start="20260708013000 +0000" stop="20260708020000 +0000" channel="airy-633">
    <title>Challenge of the GoBots</title>
    <desc>The Guardians locate a mysterious GoBot who repairs Turbo</desc>
  </programme>
  <programme start="20260708020000 +0000" stop="20260708023000 +0000" channel="airy-633">
    <title>The Herculoids</title>
    <desc>The Herculoids</desc>
  </programme>
  <programme start="20260708023000 +0000" stop="20260708030000 +0000" channel="airy-633">
    <title>The Herculoids </title>
    <desc>The Herculoids </desc>
  </programme>
  <programme start="20260708030000 +0000" stop="20260708033000 +0000" channel="airy-633">
    <title>Jayce and The Wheeled Warriors</title>
    <desc>Computer calculations give Zartan Omega as the probable location of Audric This planet is covered with blue light from the red dwarf sun and grows only giant flowers Upon reaching it though they discover Monster Minds have set up a satellite</desc>
  </programme>
  <programme start="20260708033000 +0000" stop="20260708040000 +0000" channel="airy-633">
    <title>Jayce and The Wheeled Warriors</title>
    <desc>An unconquered planet in the midst of Monster Minds intrigues the Lightning League and they go to investigate Upon crash landing they discover the energy of the Pride and the vehicles and their own energy is being drained</desc>
  </programme>
  <programme start="20260708040000 +0000" stop="20260708043000 +0000" channel="airy-633">
    <title>MASK</title>
    <desc>VENOM learn to hypnotize people through their televisions in order to help in their plans to incinerate an oil base in Texas</desc>
  </programme>
  <programme start="20260708043000 +0000" stop="20260708050000 +0000" channel="airy-633">
    <title>MASK</title>
    <desc>VENOM kidnaps a young lizard creature known as a dinosauroid</desc>
  </programme>
  <programme start="20260708050000 +0000" stop="20260708053000 +0000" channel="airy-633">
    <title>Teknoman </title>
    <desc>Legacy for the Survivors</desc>
  </programme>
  <programme start="20260708053000 +0000" stop="20260708060000 +0000" channel="airy-633">
    <title>Teknoman</title>
    <desc>The White Majin</desc>
  </programme>
  <programme start="20260708060000 +0000" stop="20260708063000 +0000" channel="airy-633">
    <title>Captain N  The Game Master</title>
    <desc>When the lost city of Kongoland arises after 1000 years the N-Team goes to investigate When they arrive an ancient treasure possesses Princess Lana with the spirit of Konga the leader of the Konkas</desc>
  </programme>
  <programme start="20260708063000 +0000" stop="20260708070000 +0000" channel="airy-633">
    <title>Captain N  The Game Master</title>
    <desc>Count Gruemon steals Kevins Power Pad and Zapper in Hyrule Kevin and Link head out to the world of Puss n Boots to retrieve the stolen items</desc>
  </programme>
  <programme start="20260708070000 +0000" stop="20260708073000 +0000" channel="airy-633">
    <title>Dungeons  Dragons</title>
    <desc>The pupils seek out and find Merlin and hell teach the pupil Presto magic if he stays with Merlin Presto decides to stay and attempts a spell to create a way home but the spell summons dragons instead which attack a nearby village</desc>
  </programme>
  <programme start="20260708073000 +0000" stop="20260708080000 +0000" channel="airy-633">
    <title>Dungeons  Dragons</title>
    <desc>The group encounters Sir John a seemingly fearless knight But hes really a coward his village is ready to exile him unless he performs one brave deed Venger captures Sir Johns son and tells him to lead the group into a trap</desc>
  </programme>
  <channel id="airy-655">
    <display-name>Cowboy Christian Network</display-name>
    <icon src="" />
  </channel>
  <programme start="20260708000000 +0000" stop="20260708010000 +0000" channel="airy-655">
    <title>Cast All Yorr Cares On Him Corey Ross CCN</title>
    <desc>Cast All Yorr Cares On Him Corey Ross CCN</desc>
  </programme>
  <programme start="20260708010000 +0000" stop="20260708020000 +0000" channel="airy-655">
    <title>Continued Spiritual Gifts Corey Ross CCN</title>
    <desc>Continued Spiritual Gifts Corey Ross CCN</desc>
  </programme>
  <programme start="20260708020000 +0000" stop="20260708030000 +0000" channel="airy-655">
    <title>Come Home Corey Ross CCN</title>
    <desc>Come Home Corey Ross CCN</desc>
  </programme>
  <programme start="20260708030000 +0000" stop="20260708040000 +0000" channel="airy-655">
    <title>Authority Part 2</title>
    <desc>Authority Part 2</desc>
  </programme>
  <programme start="20260708040000 +0000" stop="20260708050000 +0000" channel="airy-655">
    <title>Authority</title>
    <desc>Authority</desc>
  </programme>
  <programme start="20260708050000 +0000" stop="20260708060000 +0000" channel="airy-655">
    <title>Being Blessed</title>
    <desc>Being Blessed</desc>
  </programme>
  <programme start="20260708060000 +0000" stop="20260708070000 +0000" channel="airy-655">
    <title>Correcting False Teaching CCN</title>
    <desc>Correcting False Teaching CCN</desc>
  </programme>
  <programme start="20260708070000 +0000" stop="20260708080000 +0000" channel="airy-655">
    <title>Dont Be Scattered Corey Ross</title>
    <desc>Dont Be Scattered Corey Ross</desc>
  </programme>
</tv>